scorecard_mcp/__init__.py
scorecard_mcp-0.0.4.dist-info/licenses/LICENSE
scorecard_mcp-0.0.4.dist-info/METADATA
scorecard_mcp-0.0.4.dist-info/WHEEL
scorecard_mcp-0.0.4.dist-info/entry_points.txt
scorecard_mcp-0.0.4.dist-info/top_level.txt
scorecard_mcp-0.0.4.dist-info/RECORD
