Metadata-Version: 2.4
Name: scorecard-mcp
Version: 0.0.4
Summary: Basic Model Context Protocol (MCP) server for OpenSSF Scorecard
Requires-Python: >=3.10
License-File: LICENSE
Requires-Dist: httpx>=0.28.1
Requires-Dist: mcp>=1.1.3
Requires-Dist: pydantic>=2.0.0
Dynamic: license-file
